vcslinks/__init__.py
vcslinks/api.py
vcslinks/base.py
vcslinks/browse.py
vcslinks/conftest.py
vcslinks/git.py
vcslinks/py.typed
vcslinks/testing.py
vcslinks/weburl.py
vcslinks/tests/__init__.py
vcslinks/tests/test_browse.py
vcslinks/tests/test_py_typed.py
vcslinks/tests/test_weburl.py
vcslinks-0.1.2.dist-info/LICENSE
vcslinks-0.1.2.dist-info/METADATA
vcslinks-0.1.2.dist-info/WHEEL
vcslinks-0.1.2.dist-info/entry_points.txt
vcslinks-0.1.2.dist-info/top_level.txt
vcslinks-0.1.2.dist-info/RECORD
