Metadata-Version: 2.1
Name: vcslinks
Version: 0.1.2
Summary: Get URLs to commit/file/log/etc. pages in GitHub/GitLab/Bitbucket
Home-page: https://github.com/tkf/vcslinks
Author: Takafumi Arakaki
Author-email: aka.tkf@gmail.com
License: MIT
Project-URL: Tracker, https://github.com/tkf/vcslinks/issues
Platform: UNKNOWN
Classifier: Development Status :: 3 - Alpha
Classifier: License :: OSI Approved :: MIT License
Classifier: Programming Language :: Python :: 3 :: Only
Classifier: Programming Language :: Python :: 3.7
Requires-Python: >=3.7
Provides-Extra: test
Requires-Dist: pytest ; extra == 'test'
